pyorderly/__about__.py
pyorderly/__init__.py
pyorderly/core.py
pyorderly/current.py
pyorderly/read.py
pyorderly/run.py
pyorderly/outpack/__init__.py
pyorderly/outpack/config.py
pyorderly/outpack/copy_files.py
pyorderly/outpack/filestore.py
pyorderly/outpack/hash.py
pyorderly/outpack/ids.py
pyorderly/outpack/index.py
pyorderly/outpack/init.py
pyorderly/outpack/location.py
pyorderly/outpack/location_driver.py
pyorderly/outpack/location_http.py
pyorderly/outpack/location_packit.py
pyorderly/outpack/location_path.py
pyorderly/outpack/location_pull.py
pyorderly/outpack/location_push.py
pyorderly/outpack/location_ssh.py
pyorderly/outpack/metadata.py
pyorderly/outpack/oauth.py
pyorderly/outpack/packet.py
pyorderly/outpack/root.py
pyorderly/outpack/sandbox.py
pyorderly/outpack/search.py
pyorderly/outpack/search_options.py
pyorderly/outpack/static.py
pyorderly/outpack/tools.py
pyorderly/outpack/util.py
pyorderly/outpack/schema/__init__.py
pyorderly/outpack/schema/outpack/README.md
pyorderly/outpack/schema/outpack/config.json
pyorderly/outpack/schema/outpack/git.json
pyorderly/outpack/schema/outpack/hash.json
pyorderly/outpack/schema/outpack/location.json
pyorderly/outpack/schema/outpack/metadata.json
pyorderly/outpack/schema/outpack/packet-id.json
pyorderly/outpack/schema/outpack/relative-path.json
pyorderly-0.2.1.dist-info/METADATA
pyorderly-0.2.1.dist-info/WHEEL
pyorderly-0.2.1.dist-info/licenses/LICENSE.txt
pyorderly-0.2.1.dist-info/RECORD
