Metadata-Version: 2.4
Name: pyorderly
Version: 0.2.1
Summary: Reproducible and collaborative reporting
Project-URL: Documentation, https://github.com/mrc-ide/pyorderly#readme
Project-URL: Issues, https://github.com/mrc-ide/pyorderly/issues
Project-URL: Source, https://github.com/mrc-ide/pyorderly
Author-email: Rich FitzJohn <r.fitzjohn@imperial.ac.uk>
License-Expression: MIT
License-File: LICENSE.txt
Classifier: Development Status :: 4 - Beta
Classifier: Programming Language :: Python
Classifier: Programming Language :: Python :: 3.10
Classifier: Programming Language :: Python :: 3.11
Classifier: Programming Language :: Python :: 3.12
Classifier: Programming Language :: Python :: 3.13
Classifier: Programming Language :: Python :: 3.14
Classifier: Programming Language :: Python :: Implementation :: CPython
Classifier: Programming Language :: Python :: Implementation :: PyPy
Requires-Python: >=3.9
Requires-Dist: dataclasses-json
Requires-Dist: humanize
Requires-Dist: importlib-resources
Requires-Dist: jsonschema
Requires-Dist: outpack-query-parser
Requires-Dist: paramiko
Requires-Dist: pygit2
Requires-Dist: requests
Requires-Dist: tblib
Requires-Dist: typing-extensions
